moduleknife/__init__.py
moduleknife/calling.py
moduleknife/capture.py
moduleknife/display.py
moduleknife/graph.py
moduleknife/naming.py
moduleknife/ticker.py
moduleknife/commands/__init__.py
moduleknife/commands/modulegraph.py
moduleknife/commands/moduleknife.py
moduleknife/tests/__init__.py
moduleknife-0.2.1.dist-info/METADATA
moduleknife-0.2.1.dist-info/WHEEL
moduleknife-0.2.1.dist-info/entry_points.txt
moduleknife-0.2.1.dist-info/top_level.txt
moduleknife-0.2.1.dist-info/RECORD
