Metadata-Version: 2.1
Name: moduleknife
Version: 0.2.1
Summary: -
Home-page: UNKNOWN
Author: 
Author-email: 
License: UNKNOWN
Platform: UNKNOWN
Classifier: Programming Language :: Python
Classifier: Programming Language :: Python :: Implementation :: CPython
Requires-Dist: prestring
Requires-Dist: psutil
Provides-Extra: docs
Provides-Extra: testing
